RustXingnengShouce/README.md
RustXingnengShouce/__init__.py
RustXingnengShouce/__main__.py
RustXingnengShouce/file.epub
RustXingnengShouce/index.html
RustXingnengShouce/css/__init__.py
RustXingnengShouce/css/annotations.css
RustXingnengShouce/css/main.css
RustXingnengShouce/css/normalize.css
RustXingnengShouce/css/popup.css
RustXingnengShouce/font/__init__.py
RustXingnengShouce/font/fontello.eot
RustXingnengShouce/font/fontello.svg
RustXingnengShouce/font/fontello.ttf
RustXingnengShouce/font/fontello.woff
RustXingnengShouce/img/__init__.py
RustXingnengShouce/img/annotator-glyph-sprite.png
RustXingnengShouce/img/annotator-icon-sprite.png
RustXingnengShouce/img/apple-touch-icon.png
RustXingnengShouce/img/cancelfullscreen.png
RustXingnengShouce/img/close.png
RustXingnengShouce/img/fullscreen.png
RustXingnengShouce/img/loader.gif
RustXingnengShouce/img/menu-icon.png
RustXingnengShouce/img/save.png
RustXingnengShouce/img/saved.png
RustXingnengShouce/img/settings-s.png
RustXingnengShouce/img/settings.png
RustXingnengShouce/img/star.png
RustXingnengShouce/js/__init__.py
RustXingnengShouce/js/epub.js
RustXingnengShouce/js/epub.min.js
RustXingnengShouce/js/epub.min.map
RustXingnengShouce/js/hooks.min.js
RustXingnengShouce/js/hooks.min.map
RustXingnengShouce/js/reader.js
RustXingnengShouce/js/reader.js.map
RustXingnengShouce/js/reader.min.js
RustXingnengShouce/js/reader.min.map
RustXingnengShouce/js/hooks/__init__.py
RustXingnengShouce/js/hooks/extensions/__init__.py
RustXingnengShouce/js/hooks/extensions/highlight.js
RustXingnengShouce/js/libs/__init__.py
RustXingnengShouce/js/libs/jquery.min.js
RustXingnengShouce/js/libs/localforage.min.js
RustXingnengShouce/js/libs/screenfull.js
RustXingnengShouce/js/libs/screenfull.min.js
RustXingnengShouce/js/libs/zip.min.js
RustXingnengShouce/js/plugins/__init__.py
RustXingnengShouce/js/plugins/hypothesis.js
RustXingnengShouce/js/plugins/search.js
rust_xingneng_shouce-2024.3.6.0.dist-info/METADATA
rust_xingneng_shouce-2024.3.6.0.dist-info/WHEEL
rust_xingneng_shouce-2024.3.6.0.dist-info/entry_points.txt
rust_xingneng_shouce-2024.3.6.0.dist-info/top_level.txt
rust_xingneng_shouce-2024.3.6.0.dist-info/RECORD
